[
  {
    "title": "Double Angel - Shifts in Perception",
    "medium": "Free-hand Airbrush, Acrylic Paint, Arches Paper.",
    "size": "31\" x 47",
    "date": "2014–2015",
    "collab": "",
    "file": "IMG_0001",
    "link": "https://drive.google.com/file/d/1DSR8hT98VzMn8N_u3TofFlU6WiK4rUB3/view?usp=sharing"
  },
  {
    "title": "Marlene",
    "medium": "Brick, Mortar, Wood, Paper, Ash, Acrylic Paint.",
    "size": "8\" x 12",
    "date": 2015,
    "collab": "Ori Carino & Benjamin Armas",
    "file": "IMG_0022",
    "link": "https://drive.google.com/file/d/1p7ipCWrj1Qmo-fObtIKp7dvyOx-bK3o3/view?usp=sharing"
  },
  {
    "title": "3 x 12:49 am",
    "medium": "Acrylic Paint, Ash, Airbrushed on Canvas.",
    "size": "70\" x 130",
    "date": 2017,
    "collab": "Ori Carino & Benjamin Armas",
    "file": "IMG_0031",
    "link": "https://drive.google.com/file/d/1n1kd7P66JhS768-aoNoj0mh4u1KBEaho/view?usp=sharing"
  },
  {
    "title": "Dust To Dust",
    "medium": "Chrome Spraypaint, Acrylic Paint, Free-hand airbrush on Archival Cotton Rag Paper.",
    "size": "48\" x 72",
    "date": 2015,
    "collab": "Ori Carino & Benjamin Armas",
    "file": "IMG_0036",
    "link": "https://drive.google.com/file/d/1K5O9VfC-uwUmkLmjNXReCkZ3SgOwPnfi/view?usp=sharing"
  },
  {
    "title": "How to Survive Death (Facade)",
    "medium": "Recovered Brick, Mortar, Wood, Steel, Freehand Airbrush, Acrylic Paint, Mineral, Ash.",
    "size": "67\" x 45\" x 6",
    "date": 2013,
    "collab": "Ori Carino & Benjamin Armas",
    "file": "IMG_0041",
    "link": "https://drive.google.com/file/d/13ONewn_JmVOATysWjjjsx9UKUyYr2ryx/view?usp=sharing"
  },
  {
    "title": "New World",
    "medium": "Acrylic Paint, Mineral Pigment, Airbrush on Canvas.",
    "size": "72\" x 102",
    "date": 2015,
    "collab": "",
    "file": "IMG_0049",
    "link": "https://drive.google.com/file/d/1bEVRkrQni0xwBpsiSD0FANNMhQKMLMAp/view?usp=sharing"
  },
  {
    "title": "1.57am (How To Survive Death II)",
    "medium": "Brick, Mortar, Wood, Paint, Paper, Resin.",
    "size": "60\" x 38\" x 30",
    "date": "2014–2017",
    "collab": "Ori Carino & Benjamin Armas",
    "file": "IMG_0051",
    "link": "https://drive.google.com/file/d/1VXXFdPryc7kkFAO3PnDQSr2l1mOfT0Qs/view?usp=sharing"
  },
  {
    "title": "Silk and Ivory (Obsession)",
    "medium": "Free-hand Airbrush, Acrylic Paint through Silk/Cotton Blend onto Canvas with Semi-Precious Stone.",
    "size": "47\" x 35\" Frame",
    "date": "2014–2015",
    "collab": "",
    "file": "IMG_0055",
    "link": "https://drive.google.com/file/d/1We0Wfdq2y8sp3bp0FPjG7duUzIexXZTH/view?usp=sharing"
  },
  {
    "title": "Astarte",
    "medium": "Acrylic Paint, Mineral Pigment, Gold, Airbrush on Canvas.",
    "size": "52\" x 70",
    "date": 2015,
    "collab": "",
    "file": "7BAC262D-41FD-4042-89F9-507FB4F3D5ED",
    "link": "https://drive.google.com/file/d/1idFY8E4EmuxvU_-vlzh6Fbe8BUr-1z4A/view?usp=sharing"
  },
  {
    "title": "12:50 AM",
    "medium": "Acrylic Paint, Ash, Airbrushed on Canvas.",
    "size": "40\" x 60",
    "date": 2017,
    "collab": "Ori Carino & Benjamin Armas",
    "file": "IMG_0107",
    "link": "https://drive.google.com/file/d/1yUQdgzZQazQSRsyPiZ_42IyqRd-8sqGa/view?usp=sharing"
  },
  {
    "title": "The Wheel (II)",
    "medium": "Acrylic Paint, Mineral Pigment, Gold, Airbrush on Canvas.",
    "size": "54\" x 72",
    "date": 2014,
    "collab": "",
    "file": "IMG_0112",
    "link": "https://drive.google.com/file/d/1rHx1ljj3MzOY5vF3x79jWYhyLlYWOUz0/view?usp=sharing"
  }
]